dyban/__init__.py
dyban/bayesianLinearRegression.py
dyban/bayesianPwLinearRegression.py
dyban/changepointMoves.py
dyban/fpBayesianLinearRegression.py
dyban/fpGlobCoupBpwLinReg.py
dyban/fpSeqCoupBpwlinReg.py
dyban/fullParentsBpwLinReg.py
dyban/generateTestData.py
dyban/globCoupBayesianPwLinReg.py
dyban/main.py
dyban/marginalLikelihood.py
dyban/moves.py
dyban/network.py
dyban/priors.py
dyban/samplers.py
dyban/scores.py
dyban/seqCoupledBayesianPwLinReg.py
dyban/systemUtils.py
dyban/utils.py
dyban/yeast_tests.py
tests/__init__.py
tests/_utils.py
dyban-0.1.dist-info/METADATA
dyban-0.1.dist-info/WHEEL
dyban-0.1.dist-info/top_level.txt
dyban-0.1.dist-info/RECORD
