Metadata-Version: 2.1
Name: dyban
Version: 0.1
Summary: A python package that implements dynamic bayesian networks models on time series data
Home-page: https://github.com/charx7/DynamicBayesianNetworks
Author: Carlos Rodolfo Huerta Santiago
Author-email: carlos.huertaso@udlap.mx
License: UNKNOWN
Platform: UNKNOWN
Classifier: Programming Language :: Python :: 3
Classifier: License :: OSI Approved :: MIT License
Classifier: Operating System :: OS Independent
Requires-Dist: numpy (>=1.16.4)
Requires-Dist: tqdm (>=4.32.1)
Requires-Dist: scipy (>=1.3.0)
